gif_writer/__init__.py
gif_writer/__main__.py
gif_writer-0.1.0.dist-info/WHEEL
gif_writer-0.1.0.dist-info/METADATA
gif_writer-0.1.0.dist-info/RECORD
